src/__init__.py
src/checks.py
src/lookie.py
src/utilities.py
src/version.py
lookie-0.2.0.dist-info/entry_points.txt
lookie-0.2.0.dist-info/WHEEL
lookie-0.2.0.dist-info/METADATA
lookie-0.2.0.dist-info/RECORD
