Metadata-Version: 2.1
Name: lookie
Version: 0.2.0
Summary: lookie is the tool to help you monitor different kind of resources.
License: MIT
Author: fahadahammed
Author-email: iamfahadahammed@gmail.com
Requires-Python: >=3.6,<4.0
Classifier: License :: OSI Approved :: MIT License
Classifier: Programming Language :: Python :: 3
Classifier: Programming Language :: Python :: 3.10
Classifier: Programming Language :: Python :: 3.6
Classifier: Programming Language :: Python :: 3.7
Classifier: Programming Language :: Python :: 3.8
Classifier: Programming Language :: Python :: 3.9
